{
    "resource": "/telegram-webhook",
    "path": "/telegram-webhook",
    "httpMethod": "POST",
    "headers": {
      "Accept-Encoding": "gzip, deflate",
      "CloudFront-Forwarded-Proto": "https",
      "CloudFront-Is-Desktop-Viewer": "true",
      "CloudFront-Is-Mobile-Viewer": "false",
      "CloudFront-Is-SmartTV-Viewer": "false",
      "CloudFront-Is-Tablet-Viewer": "false",
      "CloudFront-Viewer-ASN": "62041",
      "CloudFront-Viewer-Country": "NL",
      "Content-Type": "application/json",
      "Host": "379v7sa0e8.execute-api.us-east-1.amazonaws.com",
      "User-Agent": "Amazon CloudFront",
      "Via": "1.1 a4ca822be9cc438f72a2d23c1e665d80.cloudfront.net (CloudFront)",
      "X-Amz-Cf-Id": "NSbnOfpPcaRNRAfzJPupTnDJKreDl57oDYWJucB13AR4EWenPemoig==",
      "X-Amzn-Trace-Id": "Root=1-667af838-3bf264586dc1c78d4f282b08",
      "X-Forwarded-For": "91.108.6.125, 15.158.40.72",
      "X-Forwarded-Port": "443",
      "X-Forwarded-Proto": "https"
    },
    "multiValueHeaders": {
      "Accept-Encoding": ["gzip, deflate"],
      "CloudFront-Forwarded-Proto": ["https"],
      "CloudFront-Is-Desktop-Viewer": ["true"],
      "CloudFront-Is-Mobile-Viewer": ["false"],
      "CloudFront-Is-SmartTV-Viewer": ["false"],
      "CloudFront-Is-Tablet-Viewer": ["false"],
      "CloudFront-Viewer-ASN": ["62041"],
      "CloudFront-Viewer-Country": ["NL"],
      "Content-Type": ["application/json"],
      "Host": ["379v7sa0e8.execute-api.us-east-1.amazonaws.com"],
      "User-Agent": ["Amazon CloudFront"],
      "Via": ["1.1 a4ca822be9cc438f72a2d23c1e665d80.cloudfront.net (CloudFront)"],
      "X-Amz-Cf-Id": ["NSbnOfpPcaRNRAfzJPupTnDJKreDl57oDYWJucB13AR4EWenPemoig=="],
      "X-Amzn-Trace-Id": ["Root=1-667af838-3bf264586dc1c78d4f282b08"],
      "X-Forwarded-For": ["91.108.6.125, 15.158.40.72"],
      "X-Forwarded-Port": ["443"],
      "X-Forwarded-Proto": ["https"]
    },
    "queryStringParameters": null,
    "multiValueQueryStringParameters": null,
    "pathParameters": null,
    "stageVariables": null,
    "requestContext": {
      "resourceId": "esv5yw",
      "resourcePath": "/telegram-webhook",
      "httpMethod": "POST",
      "extendedRequestId": "Z7u44ETfoAMEing=",
      "requestTime": "25/Jun/2024:17:02:48 +0000",
      "path": "/dev/telegram-webhook",
      "accountId": "036134507423",
      "protocol": "HTTP/1.1",
      "stage": "dev",
      "domainPrefix": "379v7sa0e8",
      "requestTimeEpoch": 1719334968527,
      "requestId": "b9d45448-1f9b-4b10-a069-b4597e355413",
      "identity": {
        "cognitoIdentityPoolId": null,
        "accountId": null,
        "cognitoIdentityId": null,
        "caller": null,
        "sourceIp": "91.108.6.125",
        "principalOrgId": null,
        "accessKey": null,
        "cognitoAuthenticationType": null,
        "cognitoAuthenticationProvider": null,
        "userArn": null,
        "userAgent": "Amazon CloudFront",
        "user": null
      },
      "domainName": "379v7sa0e8.execute-api.us-east-1.amazonaws.com",
      "deploymentId": "vh82gv",
      "apiId": "379v7sa0e8"
    },
    "body": "{\"update_id\":356402550,\"message\":{\"message_id\":12,\"from\":{\"id\":7423769471,\"is_bot\":false,\"first_name\":\"Robin\",\"last_name\":\"Ochoa\",\"language_code\":\"en\"},\"chat\":{\"id\":7423769471,\"first_name\":\"Robin\",\"last_name\":\"Ochoa\",\"type\":\"private\"},\"date\":1719332549,\"text\":\"test\"}}",
    "isBase64Encoded": false
  }